pyrandonaut/__init__.py
pyrandonaut-0.1.9.dist-info/entry_points.txt
pyrandonaut-0.1.9.dist-info/LICENSE
pyrandonaut-0.1.9.dist-info/WHEEL
pyrandonaut-0.1.9.dist-info/METADATA
pyrandonaut-0.1.9.dist-info/RECORD
